mixture/__init__.py
mixture/_version.py
mixture/core.py
mixture/tests/__init__.py
mixture/tests/utils.py
mixture/tests/core/__init__.py
mixture/tests/core/test_core_apply.py
mixture/tests/core/test_core_fields.py
mixture/tests/core/test_doc.py
mixture-0.2.1.dist-info/LICENSE
mixture-0.2.1.dist-info/METADATA
mixture-0.2.1.dist-info/WHEEL
mixture-0.2.1.dist-info/top_level.txt
mixture-0.2.1.dist-info/RECORD
