Metadata-Version: 2.1
Name: mixture
Version: 0.2.1
Summary: Mixin classes for great objects !
Home-page: https://github.com/smarie/python-mixture
Maintainer: Sylvain MARIE
Maintainer-email: sylvain.marie@se.com
License: BSD 3-Clause
Download-URL: https://github.com/smarie/python-mixture/tarball/0.2.1
Keywords: object class mixin mix-in dict yaml json dataframe pandas hash comparison munch boilerplate oop field attribute
Platform: UNKNOWN
Classifier: Development Status :: 5 - Production/Stable
Classifier: Intended Audience :: Developers
Classifier: Topic :: Software Development :: Libraries :: Python Modules
Classifier: License :: OSI Approved :: BSD License
Classifier: Programming Language :: Python :: 2.7
Classifier: Programming Language :: Python :: 3.5
Classifier: Programming Language :: Python :: 3.6
Classifier: Programming Language :: Python :: 3.7
